scpram/__init__.py
scpram/data_process.py
scpram/dataset.py
scpram/evaluate.py
scpram/models.py
scpram/utils.py
scpram/version.py
scpram-0.0.3.dist-info/LICENSE
scpram-0.0.3.dist-info/METADATA
scpram-0.0.3.dist-info/WHEEL
scpram-0.0.3.dist-info/top_level.txt
scpram-0.0.3.dist-info/RECORD
