Metadata-Version: 2.1
Name: scpram
Version: 0.0.3
Summary: scPRAM accurately predicts single-cell gene expression perturbation response based on attention mechanism
Home-page: https://github.com/jiang-q19/scPRAM
Author: Qun Jiang
License: MIT Licence
Keywords: single cell,perturbation,attention,optimal transport
Classifier: Programming Language :: Python :: 3.8
Classifier: License :: OSI Approved :: MIT License
Classifier: Operating System :: OS Independent
Requires-Python: >=3.8
License-File: LICENSE
Requires-Dist: scanpy ==1.9.3
Requires-Dist: adjusttext ==0.7
Requires-Dist: pot ==0.9.1
Requires-Dist: jupyter ==1.0.0
Requires-Dist: torch ==1.13.1
Requires-Dist: torchaudio ==0.13.1
Requires-Dist: torchvision ==0.14.1
